subproc_mgr/__init__.py
subproc_mgr/__main__.py
subproc_mgr-0.1.1.dist-info/LICENSE
subproc_mgr-0.1.1.dist-info/METADATA
subproc_mgr-0.1.1.dist-info/WHEEL
subproc_mgr-0.1.1.dist-info/top_level.txt
subproc_mgr-0.1.1.dist-info/RECORD
