Metadata-Version: 2.1
Name: subproc-mgr
Version: 0.1.1
Summary: A service to spawn and manage long-running child processes, following the lifecycle management of "child processes are attached to parent processes".
Home-page: https://github.com/thautwarm/subproc_mgr
Author: thautwarm
Author-email: twshere@outlook.com
License: mit
Keywords: subprocess,lifetime
Platform: any
Classifier: Programming Language :: Python :: 3.9
Classifier: Programming Language :: Python :: 3.10
Classifier: Programming Language :: Python :: 3.11
Classifier: Programming Language :: Python :: 3.12
Classifier: Programming Language :: Python :: Implementation :: CPython
Requires-Python: >=3.9
License-File: LICENSE
Requires-Dist: psutil
Requires-Dist: aiohttp
Requires-Dist: wisepy2
